Metadata-Version: 2.1
Name: newtools
Version: 2.2.489
Summary: Provides useful libraries for processing large data sets.
Home-page: https://bitbucket.org/deductive/newtools/
Author: Deductive
Author-email: hello@deductive.com
License: MIT
Project-URL: Documentation, https://newtools.readthedocs.io/en/latest/
Project-URL: Source, https://bitbucket.org/deductive/newtools/
Keywords: deductive
Platform: UNKNOWN
Classifier: Development Status :: 5 - Production/Stable
Classifier: Intended Audience :: Developers
Classifier: Topic :: Software Development :: Libraries
Classifier: License :: OSI Approved :: MIT License
Classifier: Programming Language :: Python :: 3.6
Requires-Python: >=3.6
Provides-Extra: full
